{
"unitID":"1904",
"title":"IA-4",
"subtitle":"Steve King (R)",
"totalTweets":111,
"keywords":[{"text":"obama","numTweets":12},{"text":"gop","numTweets":1},{"text":"gopshutdown","numTweets":0},{"text":"work","numTweets":4},{"text":"congress","numTweets":4},{"text":"house","numTweets":0},{"text":"republican","numTweets":2},{"text":"pay","numTweets":2},{"text":"obamacare","numTweets":2},{"text":"good","numTweets":1},{"text":"blame","numTweets":3},{"text":"senate","numTweets":0},{"text":"speakerboehner","numTweets":1},{"text":"shutdownthegop","numTweets":0},{"text":"barackobama","numTweets":3},{"text":"talk","numTweets":0},{"text":"school","numTweets":0},{"text":"debt","numTweets":1},{"text":"furlough","numTweets":1},{"text":"washington","numTweets":0},{"text":"worker","numTweets":1},{"text":"hope","numTweets":0},{"text":"bad","numTweets":3},{"text":"democrat","numTweets":1},{"text":"give","numTweets":0},{"text":"deal","numTweets":0},{"text":"tax","numTweets":2},{"text":"harryreidsshutdown","numTweets":0},{"text":"cruz","numTweets":0},{"text":"game","numTweets":1},{"text":"world","numTweets":1},{"text":"boehner","numTweets":1},{"text":"employee","numTweets":1},{"text":"cost","numTweets":1},{"text":"cnn","numTweets":0},{"text":"dem","numTweets":2},{"text":"money","numTweets":3},{"text":"business","numTweets":0},{"text":"budget","numTweets":1},{"text":"military","numTweets":0},{"text":"teapartyshutdown","numTweets":0},{"text":"tea","numTweets":0},{"text":"check","numTweets":2},{"text":"teaparty","numTweets":0},{"text":"food","numTweets":0},{"text":"hurt","numTweets":1},{"text":"service","numTweets":0},{"text":"cancel","numTweets":0},{"text":"negotiate","numTweets":0},{"text":"families"
,"numTweets":0}],
"demographics":[{"attribute":"pctUnemp","alias":"Percent unemployed","labelValue":"5.3 percent","chartValue":5.3},{"attribute":"pctGovWork","alias":"Percent federal government workers","labelValue":"1.563663246 percent","chartValue":1.563663246},{"attribute":"medHouseInc","alias":"Median household income","labelValue":"$47157 per year","chartValue":47157},{"attribute":"pctUnins","alias":"Percent uninsured","labelValue":"9.1 percent","chartValue":9.1},{"attribute":"cookPvi","alias":"Cook Partisan Voter Index 2012","labelValue":"R+4","chartValue":4}],
"similarUnits":[{"id":"4503","title":"SC-3"},{"id":"2801","title":"MS-1"},{"id":"0629","title":"CA-29"},{"id":"3906","title":"OH-6"},{"id":"2904","title":"MO-4"},{"id":"3404","title":"NJ-4"},{"id":"4703","title":"TN-3"},{"id":"4804","title":"TX-4"},{"id":"2605","title":"MI-5"},{"id":"3913","title":"OH-13"}],
"dissimilarUnits":[{"id":"1709","title":"IL-9"},{"id":"1212","title":"FL-12"},{"id":"0807","title":"CO-7"},{"id":"3707","title":"NC-7"},{"id":"2601","title":"MI-1"},{"id":"1203","title":"FL-3"},{"id":"2506","title":"MA-6"},{"id":"1211","title":"FL-11"},{"id":"0632","title":"CA-32"},{"id":"2610","title":"MI-10"}]
}