{
"unitID":"3401",
"title":"NJ-1",
"subtitle":"Robert E. Andrews (D)",
"totalTweets":125,
"keywords":[{"text":"obama","numTweets":13},{"text":"gop","numTweets":18},{"text":"gopshutdown","numTweets":5},{"text":"work","numTweets":6},{"text":"congress","numTweets":6},{"text":"house","numTweets":3},{"text":"republican","numTweets":7},{"text":"pay","numTweets":2},{"text":"obamacare","numTweets":3},{"text":"good","numTweets":1},{"text":"blame","numTweets":2},{"text":"senate","numTweets":3},{"text":"speakerboehner","numTweets":2},{"text":"shutdownthegop","numTweets":5},{"text":"barackobama","numTweets":4},{"text":"talk","numTweets":0},{"text":"school","numTweets":8},{"text":"debt","numTweets":1},{"text":"furlough","numTweets":0},{"text":"washington","numTweets":2},{"text":"worker","numTweets":0},{"text":"hope","numTweets":0},{"text":"bad","numTweets":0},{"text":"democrat","numTweets":0},{"text":"give","numTweets":0},{"text":"deal","numTweets":1},{"text":"tax","numTweets":1},{"text":"harryreidsshutdown","numTweets":0},{"text":"cruz","numTweets":0},{"text":"game","numTweets":2},{"text":"world","numTweets":1},{"text":"boehner","numTweets":4},{"text":"employee","numTweets":0},{"text":"cost","numTweets":1},{"text":"cnn","numTweets":0},{"text":"dem","numTweets":2},{"text":"money","numTweets":1},{"text":"business","numTweets":2},{"text":"budget","numTweets":1},{"text":"military","numTweets":2},{"text":"teapartyshutdown","numTweets":2},{"text":"tea","numTweets":6},{"text":"check","numTweets":0},{"text":"teaparty","numTweets":4},{"text":"food","numTweets":2},{"text":"hurt","numTweets":1},{"text":"service","numTweets":2},{"text":"cancel","numTweets":1},{"text":"negotiate","numTweets":0},{"text":"families"
,"numTweets":1}],
"demographics":[{"attribute":"pctUnemp","alias":"Percent unemployed","labelValue":"12.4 percent","chartValue":12.4},{"attribute":"pctGovWork","alias":"Percent federal government workers","labelValue":"2.729895515 percent","chartValue":2.729895515},{"attribute":"medHouseInc","alias":"Median household income","labelValue":"$62889 per year","chartValue":62889},{"attribute":"pctUnins","alias":"Percent uninsured","labelValue":"11 percent","chartValue":11},{"attribute":"cookPvi","alias":"Cook Partisan Voter Index 2012","labelValue":"D+12","chartValue":-12}],
"similarUnits":[{"id":"4204","title":"PA-4"},{"id":"4830","title":"TX-30"},{"id":"0107","title":"AL-7"},{"id":"4201","title":"PA-1"},{"id":"2507","title":"MA-7"},{"id":"3703","title":"NC-3"},{"id":"0103","title":"AL-3"},{"id":"1219","title":"FL-19"},{"id":"3909","title":"OH-9"},{"id":"0612","title":"CA-12"}],
"dissimilarUnits":[{"id":"1212","title":"FL-12"},{"id":"1709","title":"IL-9"},{"id":"0807","title":"CO-7"},{"id":"3707","title":"NC-7"},{"id":"2601","title":"MI-1"},{"id":"1203","title":"FL-3"},{"id":"2610","title":"MI-10"},{"id":"1211","title":"FL-11"},{"id":"2506","title":"MA-6"},{"id":"0632","title":"CA-32"}]
}