{
"unitID":"3410",
"title":"NJ-10",
"subtitle":"Donald M. Payne Jr. (D)",
"totalTweets":237,
"keywords":[{"text":"obama","numTweets":33},{"text":"gop","numTweets":89},{"text":"gopshutdown","numTweets":38},{"text":"work","numTweets":14},{"text":"congress","numTweets":6},{"text":"house","numTweets":9},{"text":"republican","numTweets":26},{"text":"pay","numTweets":21},{"text":"obamacare","numTweets":9},{"text":"good","numTweets":7},{"text":"blame","numTweets":3},{"text":"senate","numTweets":2},{"text":"speakerboehner","numTweets":6},{"text":"shutdownthegop","numTweets":16},{"text":"barackobama","numTweets":7},{"text":"talk","numTweets":5},{"text":"school","numTweets":4},{"text":"debt","numTweets":5},{"text":"furlough","numTweets":2},{"text":"washington","numTweets":2},{"text":"worker","numTweets":1},{"text":"hope","numTweets":4},{"text":"bad","numTweets":1},{"text":"democrat","numTweets":4},{"text":"give","numTweets":1},{"text":"deal","numTweets":5},{"text":"tax","numTweets":10},{"text":"harryreidsshutdown","numTweets":0},{"text":"cruz","numTweets":5},{"text":"game","numTweets":1},{"text":"world","numTweets":0},{"text":"boehner","numTweets":12},{"text":"employee","numTweets":1},{"text":"cost","numTweets":6},{"text":"cnn","numTweets":6},{"text":"dem","numTweets":19},{"text":"money","numTweets":5},{"text":"business","numTweets":4},{"text":"budget","numTweets":2},{"text":"military","numTweets":1},{"text":"teapartyshutdown","numTweets":2},{"text":"tea","numTweets":20},{"text":"check","numTweets":1},{"text":"teaparty","numTweets":15},{"text":"food","numTweets":4},{"text":"hurt","numTweets":2},{"text":"service","numTweets":0},{"text":"cancel","numTweets":0},{"text":"negotiate","numTweets":0},{"text":"families"
,"numTweets":0}],
"demographics":[{"attribute":"pctUnemp","alias":"Percent unemployed","labelValue":"16.5 percent","chartValue":16.5},{"attribute":"pctGovWork","alias":"Percent federal government workers","labelValue":"2.583591981 percent","chartValue":2.583591981},{"attribute":"medHouseInc","alias":"Median household income","labelValue":"$47083 per year","chartValue":47083},{"attribute":"pctUnins","alias":"Percent uninsured","labelValue":"18.4 percent","chartValue":18.4},{"attribute":"cookPvi","alias":"Cook Partisan Voter Index 2012","labelValue":"D+31","chartValue":-31}],
"similarUnits":[{"id":"3618","title":"NY-18"},{"id":"0648","title":"CA-48"},{"id":"2804","title":"MS-4"},{"id":"0803","title":"CO-3"},{"id":"4104","title":"OR-4"},{"id":"5502","title":"WI-2"},{"id":"3204","title":"NV-4"},{"id":"1227","title":"FL-27"},{"id":"5508","title":"WI-8"},{"id":"4831","title":"TX-31"}],
"dissimilarUnits":[{"id":"1212","title":"FL-12"},{"id":"1709","title":"IL-9"},{"id":"2610","title":"MI-10"},{"id":"0807","title":"CO-7"},{"id":"2601","title":"MI-1"},{"id":"4806","title":"TX-6"},{"id":"3707","title":"NC-7"},{"id":"0608","title":"CA-8"},{"id":"1718","title":"IL-18"},{"id":"3708","title":"NC-8"}]
}